3gpp_citations-1.0.0.data/data/examples/3gpp.bib
3gpp_citations-1.0.0.data/data/examples/3gpp_38-series.bib
3gpp_citations-1.0.0.data/scripts/3gpp-citations
3gpp_citations-1.0.0.dist-info/DESCRIPTION.rst
3gpp_citations-1.0.0.dist-info/METADATA
3gpp_citations-1.0.0.dist-info/RECORD
3gpp_citations-1.0.0.dist-info/WHEEL
3gpp_citations-1.0.0.dist-info/metadata.json
3gpp_citations-1.0.0.dist-info/top_level.txt
standardcitations/__init__.py
standardcitations/standardcitations.py
