Metadata-Version: 2.0
Name: 3gpp-citations
Version: 1.0.0
Summary: UNKNOWN
Home-page: https://github.com/martisak/3gpp-citations
Author: Martin Isaksson
Author-email: martin.isaksson@gmail.com
License: MIT License
Requires-Dist: bibtexparser (==0.6.2)
Requires-Dist: lxml (==3.8.0)
Requires-Dist: openpyxl (==2.4.8)
Requires-Dist: requests (==2.21.0)
Requires-Dist: tqdm (==4.29.1)
